bitcoinrpc/__init__.py
bitcoinrpc/authproxy.py
emercoin/__init__.py
emercoin/models.py
emercoin-0.0.4.dist-info/LICENSE
emercoin-0.0.4.dist-info/METADATA
emercoin-0.0.4.dist-info/WHEEL
emercoin-0.0.4.dist-info/top_level.txt
emercoin-0.0.4.dist-info/RECORD
