Metadata-Version: 2.1
Name: emercoin
Version: 0.0.4
Summary: Emercoin cryptocurrency API
Home-page: https://sr.ht/~cofob/Emercoin.py/
License: UNKNOWN
Platform: UNKNOWN
Requires-Python: >=3.6
License-File: LICENSE
